{"kind":"symbol","identifier":{"url":"doc:\/\/Readium\/documentation\/ReadiumNavigator\/EPUBSettings\/init(backgroundColor:columnCount:fit:fontFamily:fontSize:fontWeight:hyphens:imageFilter:language:letterSpacing:ligatures:lineHeight:offsetFirstPage:pageMargins:paragraphIndent:paragraphSpacing:publisherStyles:readingProgression:scroll:spread:textAlign:textColor:textNormalization:theme:typeScale:verticalText:wordSpacing:)","interfaceLanguage":"swift"},"sections":[],"schemaVersion":{"patch":0,"minor":3,"major":0},"primaryContentSections":[{"declarations":[{"tokens":[{"text":"init","kind":"keyword"},{"text":"(","kind":"text"},{"text":"backgroundColor","kind":"externalParam"},{"text":": ","kind":"text"},{"text":"Color","identifier":"doc:\/\/Readium\/documentation\/ReadiumNavigator\/Color","kind":"typeIdentifier","preciseIdentifier":"s:16ReadiumNavigator5ColorV"},{"text":"?, ","kind":"text"},{"text":"columnCount","kind":"externalParam"},{"text":": ","kind":"text"},{"text":"ColumnCount","identifier":"doc:\/\/Readium\/documentation\/ReadiumNavigator\/ColumnCount","kind":"typeIdentifier","preciseIdentifier":"s:16ReadiumNavigator11ColumnCountO"},{"text":", ","kind":"text"},{"text":"fit","kind":"externalParam"},{"text":": ","kind":"text"},{"text":"Fit","identifier":"doc:\/\/Readium\/documentation\/ReadiumNavigator\/Fit","kind":"typeIdentifier","preciseIdentifier":"s:16ReadiumNavigator3FitO"},{"text":", ","kind":"text"},{"text":"fontFamily","kind":"externalParam"},{"text":": ","kind":"text"},{"text":"FontFamily","identifier":"doc:\/\/Readium\/documentation\/ReadiumNavigator\/FontFamily","kind":"typeIdentifier","preciseIdentifier":"s:16ReadiumNavigator10FontFamilyV"},{"text":"?, ","kind":"text"},{"text":"fontSize","kind":"externalParam"},{"text":": ","kind":"text"},{"text":"Double","kind":"typeIdentifier","preciseIdentifier":"s:Sd"},{"text":", ","kind":"text"},{"text":"fontWeight","kind":"externalParam"},{"text":": ","kind":"text"},{"text":"Double","kind":"typeIdentifier","preciseIdentifier":"s:Sd"},{"text":"?, ","kind":"text"},{"text":"hyphens","kind":"externalParam"},{"text":": ","kind":"text"},{"text":"Bool","kind":"typeIdentifier","preciseIdentifier":"s:Sb"},{"text":"?, ","kind":"text"},{"text":"imageFilter","kind":"externalParam"},{"text":": ","kind":"text"},{"text":"ImageFilter","identifier":"doc:\/\/Readium\/documentation\/ReadiumNavigator\/ImageFilter","kind":"typeIdentifier","preciseIdentifier":"s:16ReadiumNavigator11ImageFilterO"},{"text":"?, ","kind":"text"},{"text":"language","kind":"externalParam"},{"text":": ","kind":"text"},{"text":"Language","identifier":"doc:\/\/Readium\/documentation\/ReadiumShared\/Language","kind":"typeIdentifier","preciseIdentifier":"s:13ReadiumShared8LanguageV"},{"text":"?, ","kind":"text"},{"text":"letterSpacing","kind":"externalParam"},{"text":": ","kind":"text"},{"text":"Double","kind":"typeIdentifier","preciseIdentifier":"s:Sd"},{"text":"?, ","kind":"text"},{"text":"ligatures","kind":"externalParam"},{"text":": ","kind":"text"},{"text":"Bool","kind":"typeIdentifier","preciseIdentifier":"s:Sb"},{"text":"?, ","kind":"text"},{"text":"lineHeight","kind":"externalParam"},{"text":": ","kind":"text"},{"text":"Double","kind":"typeIdentifier","preciseIdentifier":"s:Sd"},{"text":"?, ","kind":"text"},{"text":"offsetFirstPage","kind":"externalParam"},{"text":": ","kind":"text"},{"text":"Bool","kind":"typeIdentifier","preciseIdentifier":"s:Sb"},{"text":"?, ","kind":"text"},{"text":"pageMargins","kind":"externalParam"},{"text":": ","kind":"text"},{"text":"Double","kind":"typeIdentifier","preciseIdentifier":"s:Sd"},{"text":", ","kind":"text"},{"text":"paragraphIndent","kind":"externalParam"},{"text":": ","kind":"text"},{"text":"Double","kind":"typeIdentifier","preciseIdentifier":"s:Sd"},{"text":"?, ","kind":"text"},{"text":"paragraphSpacing","kind":"externalParam"},{"text":": ","kind":"text"},{"text":"Double","kind":"typeIdentifier","preciseIdentifier":"s:Sd"},{"text":"?, ","kind":"text"},{"text":"publisherStyles","kind":"externalParam"},{"text":": ","kind":"text"},{"text":"Bool","kind":"typeIdentifier","preciseIdentifier":"s:Sb"},{"text":", ","kind":"text"},{"text":"readingProgression","kind":"externalParam"},{"text":": ","kind":"text"},{"text":"ReadingProgression","identifier":"doc:\/\/Readium\/documentation\/ReadiumNavigator\/ReadingProgression","kind":"typeIdentifier","preciseIdentifier":"s:16ReadiumNavigator18ReadingProgressionO"},{"text":", ","kind":"text"},{"text":"scroll","kind":"externalParam"},{"text":": ","kind":"text"},{"text":"Bool","kind":"typeIdentifier","preciseIdentifier":"s:Sb"},{"text":", ","kind":"text"},{"text":"spread","kind":"externalParam"},{"text":": ","kind":"text"},{"text":"Spread","identifier":"doc:\/\/Readium\/documentation\/ReadiumNavigator\/Spread","kind":"typeIdentifier","preciseIdentifier":"s:16ReadiumNavigator6SpreadO"},{"text":", ","kind":"text"},{"text":"textAlign","kind":"externalParam"},{"text":": ","kind":"text"},{"text":"TextAlignment","identifier":"doc:\/\/Readium\/documentation\/ReadiumNavigator\/TextAlignment","kind":"typeIdentifier","preciseIdentifier":"s:16ReadiumNavigator13TextAlignmentO"},{"text":"?, ","kind":"text"},{"text":"textColor","kind":"externalParam"},{"text":": ","kind":"text"},{"text":"Color","identifier":"doc:\/\/Readium\/documentation\/ReadiumNavigator\/Color","kind":"typeIdentifier","preciseIdentifier":"s:16ReadiumNavigator5ColorV"},{"text":"?, ","kind":"text"},{"text":"textNormalization","kind":"externalParam"},{"text":": ","kind":"text"},{"text":"Bool","kind":"typeIdentifier","preciseIdentifier":"s:Sb"},{"text":", ","kind":"text"},{"text":"theme","kind":"externalParam"},{"text":": ","kind":"text"},{"text":"Theme","identifier":"doc:\/\/Readium\/documentation\/ReadiumNavigator\/Theme","kind":"typeIdentifier","preciseIdentifier":"s:16ReadiumNavigator5ThemeO"},{"text":", ","kind":"text"},{"text":"typeScale","kind":"externalParam"},{"text":": ","kind":"text"},{"text":"Double","kind":"typeIdentifier","preciseIdentifier":"s:Sd"},{"text":"?, ","kind":"text"},{"text":"verticalText","kind":"externalParam"},{"text":": ","kind":"text"},{"text":"Bool","kind":"typeIdentifier","preciseIdentifier":"s:Sb"},{"text":", ","kind":"text"},{"text":"wordSpacing","kind":"externalParam"},{"text":": ","kind":"text"},{"text":"Double","kind":"typeIdentifier","preciseIdentifier":"s:Sd"},{"text":"?)","kind":"text"}],"languages":["swift"],"platforms":["iOS"]}],"kind":"declarations"}],"variants":[{"paths":["\/documentation\/readiumnavigator\/epubsettings\/init(backgroundcolor:columncount:fit:fontfamily:fontsize:fontweight:hyphens:imagefilter:language:letterspacing:ligatures:lineheight:offsetfirstpage:pagemargins:paragraphindent:paragraphspacing:publisherstyles:readingprogression:scroll:sprea-3kpnf"],"traits":[{"interfaceLanguage":"swift"}]}],"hierarchy":{"paths":[["doc:\/\/Readium\/documentation\/ReadiumNavigator","doc:\/\/Readium\/documentation\/ReadiumNavigator\/EPUBSettings"]]},"metadata":{"role":"symbol","fragments":[{"text":"init","kind":"identifier"},{"text":"(","kind":"text"},{"text":"backgroundColor","kind":"externalParam"},{"text":": ","kind":"text"},{"text":"Color","kind":"typeIdentifier","preciseIdentifier":"s:16ReadiumNavigator5ColorV"},{"text":"?, ","kind":"text"},{"text":"columnCount","kind":"externalParam"},{"text":": ","kind":"text"},{"text":"ColumnCount","kind":"typeIdentifier","preciseIdentifier":"s:16ReadiumNavigator11ColumnCountO"},{"text":", ","kind":"text"},{"text":"fit","kind":"externalParam"},{"text":": ","kind":"text"},{"text":"Fit","kind":"typeIdentifier","preciseIdentifier":"s:16ReadiumNavigator3FitO"},{"text":", ","kind":"text"},{"text":"fontFamily","kind":"externalParam"},{"text":": ","kind":"text"},{"text":"FontFamily","kind":"typeIdentifier","preciseIdentifier":"s:16ReadiumNavigator10FontFamilyV"},{"text":"?, ","kind":"text"},{"text":"fontSize","kind":"externalParam"},{"text":": ","kind":"text"},{"text":"Double","kind":"typeIdentifier","preciseIdentifier":"s:Sd"},{"text":", ","kind":"text"},{"text":"fontWeight","kind":"externalParam"},{"text":": ","kind":"text"},{"text":"Double","kind":"typeIdentifier","preciseIdentifier":"s:Sd"},{"text":"?, ","kind":"text"},{"text":"hyphens","kind":"externalParam"},{"text":": ","kind":"text"},{"text":"Bool","kind":"typeIdentifier","preciseIdentifier":"s:Sb"},{"text":"?, ","kind":"text"},{"text":"imageFilter","kind":"externalParam"},{"text":": ","kind":"text"},{"text":"ImageFilter","kind":"typeIdentifier","preciseIdentifier":"s:16ReadiumNavigator11ImageFilterO"},{"text":"?, ","kind":"text"},{"text":"language","kind":"externalParam"},{"text":": ","kind":"text"},{"text":"Language","kind":"typeIdentifier","preciseIdentifier":"s:13ReadiumShared8LanguageV"},{"text":"?, ","kind":"text"},{"text":"letterSpacing","kind":"externalParam"},{"text":": ","kind":"text"},{"text":"Double","kind":"typeIdentifier","preciseIdentifier":"s:Sd"},{"text":"?, ","kind":"text"},{"text":"ligatures","kind":"externalParam"},{"text":": ","kind":"text"},{"text":"Bool","kind":"typeIdentifier","preciseIdentifier":"s:Sb"},{"text":"?, ","kind":"text"},{"text":"lineHeight","kind":"externalParam"},{"text":": ","kind":"text"},{"text":"Double","kind":"typeIdentifier","preciseIdentifier":"s:Sd"},{"text":"?, ","kind":"text"},{"text":"offsetFirstPage","kind":"externalParam"},{"text":": ","kind":"text"},{"text":"Bool","kind":"typeIdentifier","preciseIdentifier":"s:Sb"},{"text":"?, ","kind":"text"},{"text":"pageMargins","kind":"externalParam"},{"text":": ","kind":"text"},{"text":"Double","kind":"typeIdentifier","preciseIdentifier":"s:Sd"},{"text":", ","kind":"text"},{"text":"paragraphIndent","kind":"externalParam"},{"text":": ","kind":"text"},{"text":"Double","kind":"typeIdentifier","preciseIdentifier":"s:Sd"},{"text":"?, ","kind":"text"},{"text":"paragraphSpacing","kind":"externalParam"},{"text":": ","kind":"text"},{"text":"Double","kind":"typeIdentifier","preciseIdentifier":"s:Sd"},{"text":"?, ","kind":"text"},{"text":"publisherStyles","kind":"externalParam"},{"text":": ","kind":"text"},{"text":"Bool","kind":"typeIdentifier","preciseIdentifier":"s:Sb"},{"text":", ","kind":"text"},{"text":"readingProgression","kind":"externalParam"},{"text":": ","kind":"text"},{"text":"ReadingProgression","kind":"typeIdentifier","preciseIdentifier":"s:16ReadiumNavigator18ReadingProgressionO"},{"text":", ","kind":"text"},{"text":"scroll","kind":"externalParam"},{"text":": ","kind":"text"},{"text":"Bool","kind":"typeIdentifier","preciseIdentifier":"s:Sb"},{"text":", ","kind":"text"},{"text":"spread","kind":"externalParam"},{"text":": ","kind":"text"},{"text":"Spread","kind":"typeIdentifier","preciseIdentifier":"s:16ReadiumNavigator6SpreadO"},{"text":", ","kind":"text"},{"text":"textAlign","kind":"externalParam"},{"text":": ","kind":"text"},{"text":"TextAlignment","kind":"typeIdentifier","preciseIdentifier":"s:16ReadiumNavigator13TextAlignmentO"},{"text":"?, ","kind":"text"},{"text":"textColor","kind":"externalParam"},{"text":": ","kind":"text"},{"text":"Color","kind":"typeIdentifier","preciseIdentifier":"s:16ReadiumNavigator5ColorV"},{"text":"?, ","kind":"text"},{"text":"textNormalization","kind":"externalParam"},{"text":": ","kind":"text"},{"text":"Bool","kind":"typeIdentifier","preciseIdentifier":"s:Sb"},{"text":", ","kind":"text"},{"text":"theme","kind":"externalParam"},{"text":": ","kind":"text"},{"text":"Theme","kind":"typeIdentifier","preciseIdentifier":"s:16ReadiumNavigator5ThemeO"},{"text":", ","kind":"text"},{"text":"typeScale","kind":"externalParam"},{"text":": ","kind":"text"},{"text":"Double","kind":"typeIdentifier","preciseIdentifier":"s:Sd"},{"text":"?, ","kind":"text"},{"text":"verticalText","kind":"externalParam"},{"text":": ","kind":"text"},{"text":"Bool","kind":"typeIdentifier","preciseIdentifier":"s:Sb"},{"text":", ","kind":"text"},{"text":"wordSpacing","kind":"externalParam"},{"text":": ","kind":"text"},{"text":"Double","kind":"typeIdentifier","preciseIdentifier":"s:Sd"},{"text":"?)","kind":"text"}],"title":"init(backgroundColor:columnCount:fit:fontFamily:fontSize:fontWeight:hyphens:imageFilter:language:letterSpacing:ligatures:lineHeight:offsetFirstPage:pageMargins:paragraphIndent:paragraphSpacing:publisherStyles:readingProgression:scroll:spread:textAlign:textColor:textNormalization:theme:typeScale:verticalText:wordSpacing:)","externalID":"s:16ReadiumNavigator12EPUBSettingsV15backgroundColor11columnCount3fit10fontFamily0I4Size0I6Weight7hyphens11imageFilter8language13letterSpacing9ligatures10lineHeight15offsetFirstPage11pageMargins15paragraphIndent09paragraphR015publisherStyles18readingProgression6scroll6spread9textAlign04textE017textNormalization5theme9typeScale12verticalText04wordR0AcA0E0VSg_AA06ColumnG0OAA3FitOAA04FontJ0VSgS2dSgSbSgAA05ImageO0OSg0A6Shared8LanguageVSgA13_A14_A13_A14_SdA13_A13_SbAA18ReadingProgressionOSbAA6SpreadOAA13TextAlignmentOSgA5_SbAA5ThemeOA13_SbA13_tcfc","roleHeading":"Initializer","modules":[{"name":"ReadiumNavigator"}],"symbolKind":"init"},"references":{"doc://Readium/documentation/ReadiumNavigator/ReadingProgression":{"fragments":[{"kind":"keyword","text":"enum"},{"kind":"text","text":" "},{"kind":"identifier","text":"ReadingProgression"}],"kind":"symbol","abstract":[{"text":"Direction of the reading progression across resources.","type":"text"}],"navigatorTitle":[{"kind":"identifier","text":"ReadingProgression"}],"type":"topic","role":"symbol","url":"\/documentation\/readiumnavigator\/readingprogression","title":"ReadingProgression","identifier":"doc:\/\/Readium\/documentation\/ReadiumNavigator\/ReadingProgression"},"doc://Readium/documentation/ReadiumNavigator":{"url":"\/documentation\/readiumnavigator","kind":"symbol","identifier":"doc:\/\/Readium\/documentation\/ReadiumNavigator","type":"topic","abstract":[],"title":"ReadiumNavigator","role":"collection"},"doc://Readium/documentation/ReadiumNavigator/FontFamily":{"role":"symbol","abstract":[{"type":"text","text":"Typeface for a publication’s text."}],"navigatorTitle":[{"text":"FontFamily","kind":"identifier"}],"kind":"symbol","url":"\/documentation\/readiumnavigator\/fontfamily","type":"topic","title":"FontFamily","identifier":"doc:\/\/Readium\/documentation\/ReadiumNavigator\/FontFamily","fragments":[{"text":"struct","kind":"keyword"},{"text":" ","kind":"text"},{"text":"FontFamily","kind":"identifier"}]},"doc://Readium/documentation/ReadiumNavigator/Fit":{"abstract":[{"type":"text","text":"Method for fitting the content within the viewport."}],"identifier":"doc:\/\/Readium\/documentation\/ReadiumNavigator\/Fit","navigatorTitle":[{"text":"Fit","kind":"identifier"}],"role":"symbol","type":"topic","url":"\/documentation\/readiumnavigator\/fit","fragments":[{"text":"enum","kind":"keyword"},{"text":" ","kind":"text"},{"text":"Fit","kind":"identifier"}],"title":"Fit","kind":"symbol"},"doc://Readium/documentation/ReadiumNavigator/Color":{"navigatorTitle":[{"kind":"identifier","text":"Color"}],"identifier":"doc:\/\/Readium\/documentation\/ReadiumNavigator\/Color","fragments":[{"kind":"keyword","text":"struct"},{"kind":"text","text":" "},{"kind":"identifier","text":"Color"}],"title":"Color","abstract":[{"text":"Represents a color stored as a packed int.","type":"text"}],"role":"symbol","url":"\/documentation\/readiumnavigator\/color","kind":"symbol","type":"topic"},"doc://Readium/documentation/ReadiumShared/Language":{"fragments":[{"text":"struct","kind":"keyword"},{"text":" ","kind":"text"},{"text":"Language","kind":"identifier"}],"url":"\/documentation\/readiumshared\/language","navigatorTitle":[{"text":"Language","kind":"identifier"}],"type":"topic","title":"Language","identifier":"doc:\/\/Readium\/documentation\/ReadiumShared\/Language","abstract":[],"kind":"symbol","role":"symbol"},"doc://Readium/documentation/ReadiumNavigator/TextAlignment":{"role":"symbol","navigatorTitle":[{"kind":"identifier","text":"TextAlignment"}],"identifier":"doc:\/\/Readium\/documentation\/ReadiumNavigator\/TextAlignment","kind":"symbol","url":"\/documentation\/readiumnavigator\/textalignment","title":"TextAlignment","fragments":[{"kind":"keyword","text":"enum"},{"kind":"text","text":" "},{"kind":"identifier","text":"TextAlignment"}],"type":"topic","abstract":[{"text":"Text alignment in a reflowable document.","type":"text"}]},"doc://Readium/documentation/ReadiumNavigator/Spread":{"navigatorTitle":[{"text":"Spread","kind":"identifier"}],"type":"topic","role":"symbol","url":"\/documentation\/readiumnavigator\/spread","identifier":"doc:\/\/Readium\/documentation\/ReadiumNavigator\/Spread","kind":"symbol","abstract":[{"text":"Synthetic spread policy.","type":"text"}],"title":"Spread","fragments":[{"text":"enum","kind":"keyword"},{"text":" ","kind":"text"},{"text":"Spread","kind":"identifier"}]},"doc://Readium/documentation/ReadiumNavigator/ImageFilter":{"identifier":"doc:\/\/Readium\/documentation\/ReadiumNavigator\/ImageFilter","fragments":[{"kind":"keyword","text":"enum"},{"kind":"text","text":" "},{"kind":"identifier","text":"ImageFilter"}],"type":"topic","title":"ImageFilter","role":"symbol","url":"\/documentation\/readiumnavigator\/imagefilter","kind":"symbol","abstract":[{"text":"Filter used to render images in a reflowable document.","type":"text"}],"navigatorTitle":[{"kind":"identifier","text":"ImageFilter"}]},"doc://Readium/documentation/ReadiumNavigator/ColumnCount":{"type":"topic","url":"\/documentation\/readiumnavigator\/columncount","kind":"symbol","abstract":[{"type":"text","text":"Number of columns displayed in a reflowable document."}],"fragments":[{"text":"enum","kind":"keyword"},{"text":" ","kind":"text"},{"text":"ColumnCount","kind":"identifier"}],"identifier":"doc:\/\/Readium\/documentation\/ReadiumNavigator\/ColumnCount","role":"symbol","title":"ColumnCount","navigatorTitle":[{"text":"ColumnCount","kind":"identifier"}]},"doc://Readium/documentation/ReadiumNavigator/EPUBSettings/init(backgroundColor:columnCount:fit:fontFamily:fontSize:fontWeight:hyphens:imageFilter:language:letterSpacing:ligatures:lineHeight:offsetFirstPage:pageMargins:paragraphIndent:paragraphSpacing:publisherStyles:readingProgression:scroll:spread:textAlign:textColor:textNormalization:theme:typeScale:verticalText:wordSpacing:)":{"kind":"symbol","type":"topic","identifier":"doc:\/\/Readium\/documentation\/ReadiumNavigator\/EPUBSettings\/init(backgroundColor:columnCount:fit:fontFamily:fontSize:fontWeight:hyphens:imageFilter:language:letterSpacing:ligatures:lineHeight:offsetFirstPage:pageMargins:paragraphIndent:paragraphSpacing:publisherStyles:readingProgression:scroll:spread:textAlign:textColor:textNormalization:theme:typeScale:verticalText:wordSpacing:)","abstract":[],"role":"symbol","title":"init(backgroundColor:columnCount:fit:fontFamily:fontSize:fontWeight:hyphens:imageFilter:language:letterSpacing:ligatures:lineHeight:offsetFirstPage:pageMargins:paragraphIndent:paragraphSpacing:publisherStyles:readingProgression:scroll:spread:textAlign:textColor:textNormalization:theme:typeScale:verticalText:wordSpacing:)","url":"\/documentation\/readiumnavigator\/epubsettings\/init(backgroundcolor:columncount:fit:fontfamily:fontsize:fontweight:hyphens:imagefilter:language:letterspacing:ligatures:lineheight:offsetfirstpage:pagemargins:paragraphindent:paragraphspacing:publisherstyles:readingprogression:scroll:sprea-3kpnf","fragments":[{"text":"init","kind":"identifier"},{"text":"(","kind":"text"},{"text":"backgroundColor","kind":"externalParam"},{"text":": ","kind":"text"},{"text":"Color","kind":"typeIdentifier","preciseIdentifier":"s:16ReadiumNavigator5ColorV"},{"text":"?, ","kind":"text"},{"text":"columnCount","kind":"externalParam"},{"text":": ","kind":"text"},{"text":"ColumnCount","kind":"typeIdentifier","preciseIdentifier":"s:16ReadiumNavigator11ColumnCountO"},{"text":", ","kind":"text"},{"text":"fit","kind":"externalParam"},{"text":": ","kind":"text"},{"text":"Fit","kind":"typeIdentifier","preciseIdentifier":"s:16ReadiumNavigator3FitO"},{"text":", ","kind":"text"},{"text":"fontFamily","kind":"externalParam"},{"text":": ","kind":"text"},{"text":"FontFamily","kind":"typeIdentifier","preciseIdentifier":"s:16ReadiumNavigator10FontFamilyV"},{"text":"?, ","kind":"text"},{"text":"fontSize","kind":"externalParam"},{"text":": ","kind":"text"},{"text":"Double","kind":"typeIdentifier","preciseIdentifier":"s:Sd"},{"text":", ","kind":"text"},{"text":"fontWeight","kind":"externalParam"},{"text":": ","kind":"text"},{"text":"Double","kind":"typeIdentifier","preciseIdentifier":"s:Sd"},{"text":"?, ","kind":"text"},{"text":"hyphens","kind":"externalParam"},{"text":": ","kind":"text"},{"text":"Bool","kind":"typeIdentifier","preciseIdentifier":"s:Sb"},{"text":"?, ","kind":"text"},{"text":"imageFilter","kind":"externalParam"},{"text":": ","kind":"text"},{"text":"ImageFilter","kind":"typeIdentifier","preciseIdentifier":"s:16ReadiumNavigator11ImageFilterO"},{"text":"?, ","kind":"text"},{"text":"language","kind":"externalParam"},{"text":": ","kind":"text"},{"text":"Language","kind":"typeIdentifier","preciseIdentifier":"s:13ReadiumShared8LanguageV"},{"text":"?, ","kind":"text"},{"text":"letterSpacing","kind":"externalParam"},{"text":": ","kind":"text"},{"text":"Double","kind":"typeIdentifier","preciseIdentifier":"s:Sd"},{"text":"?, ","kind":"text"},{"text":"ligatures","kind":"externalParam"},{"text":": ","kind":"text"},{"text":"Bool","kind":"typeIdentifier","preciseIdentifier":"s:Sb"},{"text":"?, ","kind":"text"},{"text":"lineHeight","kind":"externalParam"},{"text":": ","kind":"text"},{"text":"Double","kind":"typeIdentifier","preciseIdentifier":"s:Sd"},{"text":"?, ","kind":"text"},{"text":"offsetFirstPage","kind":"externalParam"},{"text":": ","kind":"text"},{"text":"Bool","kind":"typeIdentifier","preciseIdentifier":"s:Sb"},{"text":"?, ","kind":"text"},{"text":"pageMargins","kind":"externalParam"},{"text":": ","kind":"text"},{"text":"Double","kind":"typeIdentifier","preciseIdentifier":"s:Sd"},{"text":", ","kind":"text"},{"text":"paragraphIndent","kind":"externalParam"},{"text":": ","kind":"text"},{"text":"Double","kind":"typeIdentifier","preciseIdentifier":"s:Sd"},{"text":"?, ","kind":"text"},{"text":"paragraphSpacing","kind":"externalParam"},{"text":": ","kind":"text"},{"text":"Double","kind":"typeIdentifier","preciseIdentifier":"s:Sd"},{"text":"?, ","kind":"text"},{"text":"publisherStyles","kind":"externalParam"},{"text":": ","kind":"text"},{"text":"Bool","kind":"typeIdentifier","preciseIdentifier":"s:Sb"},{"text":", ","kind":"text"},{"text":"readingProgression","kind":"externalParam"},{"text":": ","kind":"text"},{"text":"ReadingProgression","kind":"typeIdentifier","preciseIdentifier":"s:16ReadiumNavigator18ReadingProgressionO"},{"text":", ","kind":"text"},{"text":"scroll","kind":"externalParam"},{"text":": ","kind":"text"},{"text":"Bool","kind":"typeIdentifier","preciseIdentifier":"s:Sb"},{"text":", ","kind":"text"},{"text":"spread","kind":"externalParam"},{"text":": ","kind":"text"},{"text":"Spread","kind":"typeIdentifier","preciseIdentifier":"s:16ReadiumNavigator6SpreadO"},{"text":", ","kind":"text"},{"text":"textAlign","kind":"externalParam"},{"text":": ","kind":"text"},{"text":"TextAlignment","kind":"typeIdentifier","preciseIdentifier":"s:16ReadiumNavigator13TextAlignmentO"},{"text":"?, ","kind":"text"},{"text":"textColor","kind":"externalParam"},{"text":": ","kind":"text"},{"text":"Color","kind":"typeIdentifier","preciseIdentifier":"s:16ReadiumNavigator5ColorV"},{"text":"?, ","kind":"text"},{"text":"textNormalization","kind":"externalParam"},{"text":": ","kind":"text"},{"text":"Bool","kind":"typeIdentifier","preciseIdentifier":"s:Sb"},{"text":", ","kind":"text"},{"text":"theme","kind":"externalParam"},{"text":": ","kind":"text"},{"text":"Theme","kind":"typeIdentifier","preciseIdentifier":"s:16ReadiumNavigator5ThemeO"},{"text":", ","kind":"text"},{"text":"typeScale","kind":"externalParam"},{"text":": ","kind":"text"},{"text":"Double","kind":"typeIdentifier","preciseIdentifier":"s:Sd"},{"text":"?, ","kind":"text"},{"text":"verticalText","kind":"externalParam"},{"text":": ","kind":"text"},{"text":"Bool","kind":"typeIdentifier","preciseIdentifier":"s:Sb"},{"text":", ","kind":"text"},{"text":"wordSpacing","kind":"externalParam"},{"text":": ","kind":"text"},{"text":"Double","kind":"typeIdentifier","preciseIdentifier":"s:Sd"},{"text":"?)","kind":"text"}]},"doc://Readium/documentation/ReadiumNavigator/EPUBSettings":{"fragments":[{"kind":"keyword","text":"struct"},{"kind":"text","text":" "},{"kind":"identifier","text":"EPUBSettings"}],"kind":"symbol","type":"topic","role":"symbol","title":"EPUBSettings","abstract":[{"type":"text","text":"Setting values of the "},{"type":"codeVoice","code":"EPUBNavigatorViewController"},{"type":"text","text":"."}],"url":"\/documentation\/readiumnavigator\/epubsettings","identifier":"doc:\/\/Readium\/documentation\/ReadiumNavigator\/EPUBSettings","navigatorTitle":[{"kind":"identifier","text":"EPUBSettings"}]},"doc://Readium/documentation/ReadiumNavigator/Theme":{"kind":"symbol","type":"topic","role":"symbol","title":"Theme","identifier":"doc:\/\/Readium\/documentation\/ReadiumNavigator\/Theme","fragments":[{"kind":"keyword","text":"enum"},{"kind":"text","text":" "},{"kind":"identifier","text":"Theme"}],"navigatorTitle":[{"kind":"identifier","text":"Theme"}],"url":"\/documentation\/readiumnavigator\/theme","abstract":[{"type":"text","text":"Reader theme for reflowable documents."}]}}}